tp1/alu.v
// iverilog -o tb_alu tb_alu.v          iverilog -o tb_alu tb_alu.v alu.v     Me anduvo asi no c porque
// vvp tb_alu
// gtkwave alu.vcd                 (en el testbench vas a tener que definir que se cree el test.vcd)

// Implementar en FPGA una ALU:
//  - La ALU debe ser parametrizable (bus de datos) para poder ser utilizada posteriormente
//  - Validar el desarrollo con test bench
//      - Debe incluir generacion de entradas aleatorias y codigo de chequeo
//  - Simular el diseno usando vivado con analisis de tiempo

//  ADD     100000
//  SUB     100010
//  AND     100100
//  OR      100101
//  XOR     100110
//  SRA     000011
//  SRL     000010
//  NOR     100111  

module ALU 
#(
    parameter NB_DATA = 8,
    parameter NB_OP = 6
)
(
    input wire signed [NB_DATA - 1 : 0] i_data_a,   // 8 bits para a
    input wire signed [NB_DATA - 1 : 0] i_data_b,   // 8 bits para b
    input wire signed [NB_DATA - 1 : 0] i_op,       // 8 bits para operador
    // input        FALTAN LOS SW 1 2 3
    output wire signed [NB_OP - 1 : 0] o_data       // Salida de la alu
);

reg [NB_DATA - 1 : 0] tmp ;     // Registro para almacenar calculo, y despues pasarlo a la salida

//always @(posedge sw_1) begin
always @(*) 
begin
    case (i_op)
        6'b100000: tmp = i_data_a + i_data_b;       // Operación ADD
        6'b100010: tmp = i_data_a - i_data_b;       // Operación SUB
        6'b100100: tmp = i_data_a & i_data_b;       // Operación AND
        6'b100101: tmp = i_data_a | i_data_b;       // Operación OR
        6'b100110: tmp = i_data_a ^ i_data_b;       // Operación XOR
        6'b000011: tmp = i_data_a >>> 1;            // Operación SRA
        6'b000010: tmp = i_data_a >> 1;             // Operación SRL
        6'b100111: tmp = ~(i_data_a | i_data_b);    // Operación NOR
        default: tmp = 0;
    endcase
end

assign o_data = tmp;        // esto conecta el registro tmp con la salida o_data (imagina que son cables, registro a puerto)
    
endmodule

tp1/tb_alu.v
`timescale 1ns/1ps

module tb_ALU;

parameter NB_DATA = 8;
parameter NB_OP = 6;

// localparam AND = 100100;

// Señales
reg signed [NB_DATA-1:0] i_data_a;
reg signed [NB_DATA-1:0] i_data_b;
reg [NB_OP-1:0] i_op;
wire signed [NB_DATA-1:0] o_data;

// Instanciar la ALU
ALU #(
    .NB_DATA(NB_DATA),
    .NB_OP(NB_OP)
) uut (
    .i_data_a(i_data_a),
    .i_data_b(i_data_b),
    .i_op(i_op),
    .o_data(o_data)
);

// Archivo para el VCD
initial begin
    $dumpfile("alu.vcd");
    $dumpvars(0, tb_ALU);

    // Prueba 1: ADD
    i_data_a = 8'd10;
    i_data_b = 8'd15;
    i_op = 6'b100000; // ADD
    #10;

    // Prueba 2: SUB
    i_data_a = 8'd20;
    i_data_b = 8'd5;
    i_op = 6'b100010; // SUB
    #10;

    // Prueba 3: AND
    i_data_a = 8'b10101010;
    i_data_b = 8'b11001100;
    i_op = 6'b100100; // AND
    #10;

    // Prueba 4: OR
    i_data_a = 8'b10101010;
    i_data_b = 8'b11001100;
    i_op = 6'b100101; // OR
    #10;

    // Prueba 5: XOR
    i_data_a = 8'b10101010;
    i_data_b = 8'b11001100;
    i_op = 6'b100110; // XOR
    #10;

    // Prueba 6: SRA
    i_data_a = 8'b10101010;
    i_op = 6'b000011; // SRA
    #10;

    // Prueba 7: SRL
    i_data_a = 8'b10101010;
    i_op = 6'b000010; // SRL
    #10;

    // Prueba 8: NOR
    i_data_a = 8'b10101010;
    i_data_b = 8'b11001100;
    i_op = 6'b100111; // NOR
    #10;

    $finish;
end

endmodule

tp1/alu.vcd
$date
	Thu Sep  5 08:59:15 2024
$end
$version
	Icarus Verilog
$end
$timescale
	1ps
$end
$scope module tb_ALU $end
$var wire 8 ! o_data [7:0] $end
$var parameter 32 " NB_DATA $end
$var parameter 32 # NB_OP $end
$var reg 8 $ i_data_a [7:0] $end
$var reg 8 % i_data_b [7:0] $end
$var reg 6 & i_op [5:0] $end
$scope module uut $end
$var wire 8 ' i_data_a [7:0] $end
$var wire 8 ( i_data_b [7:0] $end
$var wire 8 ) i_op [7:0] $end
$var wire 6 * o_data [5:0] $end
$var parameter 32 + NB_DATA $end
$var parameter 32 , NB_OP $end
$var reg 8 - tmp [7:0] $end
$upscope $end
$upscope $end
$enddefinitions $end
$comment Show the parameter values. $end
$dumpall
b110 ,
b1000 +
b110 #
b1000 "
$end
#0
$dumpvars
b11001 -
b11001 *
b100000 )
b1111 (
b1010 '
b100000 &
b1111 %
b1010 $
b11001 !
$end
#10000
b1111 !
b1111 *
b1111 -
b100010 )
b100010 &
b101 %
b101 (
b10100 $
b10100 '
#20000
b1000 !
b1000 *
b10001000 -
b100100 )
b100100 &
b11001100 %
b11001100 (
b10101010 $
b10101010 '
#30000
b11101110 !
b101110 *
b11101110 -
b100101 )
b100101 &
#40000
b11100110 !
b100110 *
b1100110 -
b100110 )
b100110 &
#50000
b10101 !
b10101 *
b11010101 -
b11 )
b11 &
#60000
b1010101 -
b10 )
b10 &
#70000
b10001 !
b10001 *
b10001 -
b100111 )
b100111 &
